oem_client_provider_package/__init__.py
oem_client_provider_package/main.py
oem_client_provider_package-1.1.1.dist-info/DESCRIPTION.rst
oem_client_provider_package-1.1.1.dist-info/METADATA
oem_client_provider_package-1.1.1.dist-info/RECORD
oem_client_provider_package-1.1.1.dist-info/WHEEL
oem_client_provider_package-1.1.1.dist-info/metadata.json
oem_client_provider_package-1.1.1.dist-info/pbr.json
oem_client_provider_package-1.1.1.dist-info/top_level.txt
